CMakeLists.txt
MANIFEST.in
ReadMe.rst
generate.py
setup.py
cmake/Event.cmake
cmake/Exec.cmake
cmake/IO.cmake
cmake/Logger.cmake
cmake/PluginLoader.cmake
cmake/Proto.cmake
cmake/Status.cmake
cmake/World.cmake
include/byteswap.hpp
include/datautils.hpp
include/event_core.hpp
include/exec_core.hpp
include/gui_core.hpp
include/io_core.hpp
include/logger.hpp
include/nbt.hpp
include/physics.hpp
include/plugin_base.hpp
include/plugin_loader.hpp
include/smpmap.hpp
include/status_core.hpp
include/world_core.hpp
mcd2cpp/__init__.py
mcd2cpp/block_data.hpp
mcd2cpp/blocks.py
mcd2cpp/particles.py
mcd2cpp/protocol.py
mcd2cpp/shape_data.hpp
mcd2cpp/shapes.py
mcd2cpp/__pycache__/__init__.cpython-38.pyc
mcd2cpp/__pycache__/__init__.cpython-39.pyc
mcd2cpp/__pycache__/blocks.cpython-38.pyc
mcd2cpp/__pycache__/blocks.cpython-39.pyc
mcd2cpp/__pycache__/particles.cpython-38.pyc
mcd2cpp/__pycache__/particles.cpython-39.pyc
mcd2cpp/__pycache__/protocol.cpython-38.pyc
mcd2cpp/__pycache__/protocol.cpython-39.pyc
mcd2cpp/__pycache__/shapes.cpython-39.pyc
rikerbot/CLogger.py
rikerbot/CPluginLoader.py
rikerbot/DependencySolver.py
rikerbot/PluginBase.py
rikerbot/PluginLoader.py
rikerbot/SimpleClient.py
rikerbot/__init__.py
rikerbot.egg-info/PKG-INFO
rikerbot.egg-info/SOURCES.txt
rikerbot.egg-info/dependency_links.txt
rikerbot.egg-info/top_level.txt
rikerbot/plugins/AuthPlugin.py
rikerbot/plugins/CEventCore.py
rikerbot/plugins/CExecCore.py
rikerbot/plugins/CIOCore.py
rikerbot/plugins/CStatusCore.py
rikerbot/plugins/CWorldCore.py
rikerbot/plugins/EventPlugin.py
rikerbot/plugins/ExecPlugin.py
rikerbot/plugins/GuiPlugin.py
rikerbot/plugins/IOPlugin.py
rikerbot/plugins/KeepAlive.py
rikerbot/plugins/StartPlugin.py
rikerbot/plugins/StatusPlugin.py
rikerbot/plugins/WorldPlugin.py
rikerbot/plugins/__init__.py
rikerbot/proto/MinecraftProtocol.py
rikerbot/proto/Proto1_16_4.py
rikerbot/proto/__init__.py
rikerbot/proto/yggdrasil.py
src/datautils.cpp
src/event_core.cpp
src/exec_core.cpp
src/gui_core.cpp
src/io_core.cpp
src/logger.cpp
src/physics.cpp
src/plugin_base.cpp
src/plugin_loader.cpp
src/smpmap.cpp
src/status_core.cpp
