Metadata-Version: 1.1
Name: rikerbot
Version: 0.0.2
Summary: RikerBot is a framework for creating Python Minecraft Bots with C++ extensions
Home-page: https://github.com/SpockBotMC/RikerBot
Author: N. Vito Gamberini
Author-email: vito@gamberini.email
License: zlib
Keywords: minecraft
Platform: UNKNOWN
Classifier: Development Status :: 2 - Pre-Alpha
Classifier: License :: OSI Approved :: zlib/libpng License
Classifier: Programming Language :: C++
Classifier: Programming Language :: Python :: 3 :: Only
